django_xray-0.1.0.dist-info/DESCRIPTION.rst
django_xray-0.1.0.dist-info/METADATA
django_xray-0.1.0.dist-info/metadata.json
django_xray-0.1.0.dist-info/RECORD
django_xray-0.1.0.dist-info/top_level.txt
django_xray-0.1.0.dist-info/WHEEL
xray/__init__.py
xray/models.py
xray/urls.py
xray/views.py
