Metadata-Version: 2.0
Name: django-xray
Version: 0.1.0
Summary: Xray is an developer helper tool for Django.
Home-page: https://github.com/kindy/django-xray
Author: Kindy Lin
Author-email: kindy61@gmail.com
License: MIT
Platform: UNKNOWN
Classifier: Environment :: Web Environment
Classifier: Intended Audience :: Developers
Classifier: Development Status :: 3 - Alpha
Classifier: License :: OSI Approved :: MIT License
Classifier: Operating System :: OS Independent
Classifier: Programming Language :: Python
Classifier: Programming Language :: Python :: 3
Classifier: Topic :: Utilities
Requires-Dist: docutils
